{
    "Jan": {
        "B000VSM4MS": {
            "title": "Crescent MG38-PK 38\" Acoustic Guitar Starter Package, PINK (Includes CrescentTM Digital E-Tuner)",
            "avg_ratings": 3.66743648960739,
            "num_ratings": 866,
            "brand": "Crescent",
            "sub_categories": [
                "Musical Instruments",
                "Guitars",
                "Acoustic Guitars",
                "Steel-string Acoustics"
            ]
        },
        "B000XI6O2W": {
            "title": "Singing Machine SMM-205 Unidirectional Dynamic Microphone with 10 Ft. Cord",
            "avg_ratings": 4.079081632653061,
            "num_ratings": 784,
            "brand": "Singing Machine",
            "sub_categories": [
                "Musical Instruments",
                "Microphones & Accessories",
                "Microphones",
                "Dynamic Microphones",
                "Vocal"
            ]
        },
        "B00IFOTSJW": {
            "title": "Snark SN1 Guitar Tuner (Blue)",
            "avg_ratings": 4.613240418118467,
            "num_ratings": 574,
            "brand": "Snark",
            "sub_categories": [
                "Musical Instruments",
                "Instrument Accessories",
                "Guitar & Bass Accessories",
                "Tuners"
            ]
        },
        "B004XNK7AI": {
            "title": "Snark SN-5 Tuner for Guitar, Bass and Violin (Black)",
            "avg_ratings": 4.613043478260869,
            "num_ratings": 460,
            "brand": "Snark",
            "sub_categories": [
                "Musical Instruments",
                "Instrument Accessories",
                "Guitar & Bass Accessories",
                "Tuners"
            ]
        },
        "B002026DR0": {
            "title": "Mendini 4/4 MV300 Solid Wood Satin Antique Violin with Hard Case, Shoulder Rest, Bow, Rosin and Extra Strings (Full Size)",
            "avg_ratings": 3.3811764705882354,
            "num_ratings": 425,
            "brand": "Mendini",
            "sub_categories": [
                "Musical Instruments",
                "Band & Orchestra",
                "Orchestral Strings",
                "Violins",
                "Acoustic Violins"
            ]
        },
        "B0006NDF8A": {
            "title": "On-Stage XCG4 Black Tripod Guitar Stand, Single",
            "avg_ratings": 4.45933014354067,
            "num_ratings": 418,
            "brand": "OnStage",
            "sub_categories": [
                "Musical Instruments",
                "Instrument Accessories",
                "Guitar & Bass Accessories"
            ]
        },
        "B0002E1NWI": {
            "title": "Elixir Strings 80/20 Bronze Acoustic Guitar Strings w POLYWEB Coating, Light/Medium (.012-.056)",
            "avg_ratings": 4.706329113924051,
            "num_ratings": 395,
            "brand": "Elixir",
            "sub_categories": [
                "Musical Instruments",
                "Instrument Accessories",
                "Guitar & Bass Accessories",
                "Strings",
                "Acoustic Guitar Strings"
            ]
        },
        "B0002E1NNC": {
            "title": "Elixir Strings 80/20 Bronze Acoustic Guitar Strings w POLYWEB Coating, Extra Light (.010-.047)",
            "avg_ratings": 4.706329113924051,
            "num_ratings": 395,
            "brand": "Elixir",
            "sub_categories": [
                "Musical Instruments",
                "Instrument Accessories",
                "Guitar & Bass Accessories",
                "Strings",
                "Acoustic Guitar Strings"
            ]
        },
        "B00XQFONF4": {
            "title": "Dragonpad USA 6\" Microphone Studio Pop Filter with Clamp - Pink/White",
            "avg_ratings": 4.111675126903553,
            "num_ratings": 394,
            "brand": "DragonPad USA",
            "sub_categories": [
                "Musical Instruments",
                "Microphones & Accessories",
                "Accessories",
                "Windscreens & Pop Filters"
            ]
        },
        "B00DY1F2CS": {
            "title": "NEEWER Adjustable Microphone Suspension Boom Scissor Arm Stand, Max Load 1 KG Compact Mic Stand Made of Durable Steel for Radio Broadcasting Studio, Voice-Over Sound Studio, Stages, and TV Stations",
            "avg_ratings": 3.893617021276596,
            "num_ratings": 376,
            "brand": "Neewer",
            "sub_categories": [
                "Musical Instruments",
                "Microphones & Accessories",
                "Accessories",
                "Stands"
            ]
        }
    },
    "Feb": {
        "B000VSM4MS": {
            "title": "Crescent MG38-PK 38\" Acoustic Guitar Starter Package, PINK (Includes CrescentTM Digital E-Tuner)",
            "avg_ratings": 3.3296296296296295,
            "num_ratings": 540,
            "brand": "Crescent",
            "sub_categories": [
                "Musical Instruments",
                "Guitars",
                "Acoustic Guitars",
                "Steel-string Acoustics"
            ]
        },
        "B000XI6O2W": {
            "title": "Singing Machine SMM-205 Unidirectional Dynamic Microphone with 10 Ft. Cord",
            "avg_ratings": 3.9047619047619047,
            "num_ratings": 462,
            "brand": "Singing Machine",
            "sub_categories": [
                "Musical Instruments",
                "Microphones & Accessories",
                "Microphones",
                "Dynamic Microphones",
                "Vocal"
            ]
        },
        "B00IFOTSJW": {
            "title": "Snark SN1 Guitar Tuner (Blue)",
            "avg_ratings": 4.686915887850467,
            "num_ratings": 428,
            "brand": "Snark",
            "sub_categories": [
                "Musical Instruments",
                "Instrument Accessories",
                "Guitar & Bass Accessories",
                "Tuners"
            ]
        },
        "B004XNK7AI": {
            "title": "Snark SN-5 Tuner for Guitar, Bass and Violin (Black)",
            "avg_ratings": 4.637469586374696,
            "num_ratings": 411,
            "brand": "Snark",
            "sub_categories": [
                "Musical Instruments",
                "Instrument Accessories",
                "Guitar & Bass Accessories",
                "Tuners"
            ]
        },
        "B00XQFONF4": {
            "title": "Dragonpad USA 6\" Microphone Studio Pop Filter with Clamp - Pink/White",
            "avg_ratings": 4.060773480662983,
            "num_ratings": 362,
            "brand": "DragonPad USA",
            "sub_categories": [
                "Musical Instruments",
                "Microphones & Accessories",
                "Accessories",
                "Windscreens & Pop Filters"
            ]
        },
        "B00DY1F2CS": {
            "title": "NEEWER Adjustable Microphone Suspension Boom Scissor Arm Stand, Max Load 1 KG Compact Mic Stand Made of Durable Steel for Radio Broadcasting Studio, Voice-Over Sound Studio, Stages, and TV Stations",
            "avg_ratings": 3.860182370820669,
            "num_ratings": 329,
            "brand": "Neewer",
            "sub_categories": [
                "Musical Instruments",
                "Microphones & Accessories",
                "Accessories",
                "Stands"
            ]
        },
        "B0007Y09VO": {
            "title": "D'Addario EJ17-B25 Phosphor Bronze Acoustic Guitar Strings, Medium, 13-56, 25 Bulk Sets",
            "avg_ratings": 4.613924050632911,
            "num_ratings": 316,
            "brand": "D'Addario",
            "sub_categories": [
                "Musical Instruments",
                "Instrument Accessories",
                "Guitar & Bass Accessories",
                "Strings",
                "Acoustic Guitar Strings"
            ]
        },
        "B0002H0A3S": {
            "title": "D'Addario EJ26 Phosphor Bronze Acoustic Guitar Strings, Custom Light, 11-52",
            "avg_ratings": 4.613924050632911,
            "num_ratings": 316,
            "brand": "D'Addario",
            "sub_categories": [
                "Musical Instruments",
                "Instrument Accessories",
                "Guitar & Bass Accessories",
                "Strings",
                "Acoustic Guitar Strings"
            ]
        },
        "B0002E1NWI": {
            "title": "Elixir Strings 80/20 Bronze Acoustic Guitar Strings w POLYWEB Coating, Light/Medium (.012-.056)",
            "avg_ratings": 4.601910828025478,
            "num_ratings": 314,
            "brand": "Elixir",
            "sub_categories": [
                "Musical Instruments",
                "Instrument Accessories",
                "Guitar & Bass Accessories",
                "Strings",
                "Acoustic Guitar Strings"
            ]
        },
        "B0002E1NNC": {
            "title": "Elixir Strings 80/20 Bronze Acoustic Guitar Strings w POLYWEB Coating, Extra Light (.010-.047)",
            "avg_ratings": 4.601910828025478,
            "num_ratings": 314,
            "brand": "Elixir",
            "sub_categories": [
                "Musical Instruments",
                "Instrument Accessories",
                "Guitar & Bass Accessories",
                "Strings",
                "Acoustic Guitar Strings"
            ]
        }
    },
    "Mar": {
        "B000VSM4MS": {
            "title": "Crescent MG38-PK 38\" Acoustic Guitar Starter Package, PINK (Includes CrescentTM Digital E-Tuner)",
            "avg_ratings": 3.3875,
            "num_ratings": 480,
            "brand": "Crescent",
            "sub_categories": [
                "Musical Instruments",
                "Guitars",
                "Acoustic Guitars",
                "Steel-string Acoustics"
            ]
        },
        "B004XNK7AI": {
            "title": "Snark SN-5 Tuner for Guitar, Bass and Violin (Black)",
            "avg_ratings": 4.743040685224839,
            "num_ratings": 467,
            "brand": "Snark",
            "sub_categories": [
                "Musical Instruments",
                "Instrument Accessories",
                "Guitar & Bass Accessories",
                "Tuners"
            ]
        },
        "B00XQFONF4": {
            "title": "Dragonpad USA 6\" Microphone Studio Pop Filter with Clamp - Pink/White",
            "avg_ratings": 4.147392290249433,
            "num_ratings": 441,
            "brand": "DragonPad USA",
            "sub_categories": [
                "Musical Instruments",
                "Microphones & Accessories",
                "Accessories",
                "Windscreens & Pop Filters"
            ]
        },
        "B00IFOTSJW": {
            "title": "Snark SN1 Guitar Tuner (Blue)",
            "avg_ratings": 4.7134986225895315,
            "num_ratings": 363,
            "brand": "Snark",
            "sub_categories": [
                "Musical Instruments",
                "Instrument Accessories",
                "Guitar & Bass Accessories",
                "Tuners"
            ]
        },
        "B00DY1F2CS": {
            "title": "NEEWER Adjustable Microphone Suspension Boom Scissor Arm Stand, Max Load 1 KG Compact Mic Stand Made of Durable Steel for Radio Broadcasting Studio, Voice-Over Sound Studio, Stages, and TV Stations",
            "avg_ratings": 3.9833333333333334,
            "num_ratings": 360,
            "brand": "Neewer",
            "sub_categories": [
                "Musical Instruments",
                "Microphones & Accessories",
                "Accessories",
                "Stands"
            ]
        },
        "B000XI6O2W": {
            "title": "Singing Machine SMM-205 Unidirectional Dynamic Microphone with 10 Ft. Cord",
            "avg_ratings": 3.95,
            "num_ratings": 360,
            "brand": "Singing Machine",
            "sub_categories": [
                "Musical Instruments",
                "Microphones & Accessories",
                "Microphones",
                "Dynamic Microphones",
                "Vocal"
            ]
        },
        "B0007Y09VO": {
            "title": "D'Addario EJ17-B25 Phosphor Bronze Acoustic Guitar Strings, Medium, 13-56, 25 Bulk Sets",
            "avg_ratings": 4.608938547486034,
            "num_ratings": 358,
            "brand": "D'Addario",
            "sub_categories": [
                "Musical Instruments",
                "Instrument Accessories",
                "Guitar & Bass Accessories",
                "Strings",
                "Acoustic Guitar Strings"
            ]
        },
        "B0002H0A3S": {
            "title": "D'Addario EJ26 Phosphor Bronze Acoustic Guitar Strings, Custom Light, 11-52",
            "avg_ratings": 4.608938547486034,
            "num_ratings": 358,
            "brand": "D'Addario",
            "sub_categories": [
                "Musical Instruments",
                "Instrument Accessories",
                "Guitar & Bass Accessories",
                "Strings",
                "Acoustic Guitar Strings"
            ]
        },
        "B0006NDF8A": {
            "title": "On-Stage XCG4 Black Tripod Guitar Stand, Single",
            "avg_ratings": 4.435582822085889,
            "num_ratings": 326,
            "brand": "OnStage",
            "sub_categories": [
                "Musical Instruments",
                "Instrument Accessories",
                "Guitar & Bass Accessories"
            ]
        },
        "B0002E1NWI": {
            "title": "Elixir Strings 80/20 Bronze Acoustic Guitar Strings w POLYWEB Coating, Light/Medium (.012-.056)",
            "avg_ratings": 4.533950617283951,
            "num_ratings": 324,
            "brand": "Elixir",
            "sub_categories": [
                "Musical Instruments",
                "Instrument Accessories",
                "Guitar & Bass Accessories",
                "Strings",
                "Acoustic Guitar Strings"
            ]
        }
    },
    "Apr": {
        "B004XNK7AI": {
            "title": "Snark SN-5 Tuner for Guitar, Bass and Violin (Black)",
            "avg_ratings": 4.66256157635468,
            "num_ratings": 406,
            "brand": "Snark",
            "sub_categories": [
                "Musical Instruments",
                "Instrument Accessories",
                "Guitar & Bass Accessories",
                "Tuners"
            ]
        },
        "B000VSM4MS": {
            "title": "Crescent MG38-PK 38\" Acoustic Guitar Starter Package, PINK (Includes CrescentTM Digital E-Tuner)",
            "avg_ratings": 3.4190751445086707,
            "num_ratings": 346,
            "brand": "Crescent",
            "sub_categories": [
                "Musical Instruments",
                "Guitars",
                "Acoustic Guitars",
                "Steel-string Acoustics"
            ]
        },
        "B00DY1F2CS": {
            "title": "NEEWER Adjustable Microphone Suspension Boom Scissor Arm Stand, Max Load 1 KG Compact Mic Stand Made of Durable Steel for Radio Broadcasting Studio, Voice-Over Sound Studio, Stages, and TV Stations",
            "avg_ratings": 3.861842105263158,
            "num_ratings": 304,
            "brand": "Neewer",
            "sub_categories": [
                "Musical Instruments",
                "Microphones & Accessories",
                "Accessories",
                "Stands"
            ]
        },
        "B00IFOTSJW": {
            "title": "Snark SN1 Guitar Tuner (Blue)",
            "avg_ratings": 4.674740484429066,
            "num_ratings": 289,
            "brand": "Snark",
            "sub_categories": [
                "Musical Instruments",
                "Instrument Accessories",
                "Guitar & Bass Accessories",
                "Tuners"
            ]
        },
        "B0002E1NWI": {
            "title": "Elixir Strings 80/20 Bronze Acoustic Guitar Strings w POLYWEB Coating, Light/Medium (.012-.056)",
            "avg_ratings": 4.533101045296167,
            "num_ratings": 287,
            "brand": "Elixir",
            "sub_categories": [
                "Musical Instruments",
                "Instrument Accessories",
                "Guitar & Bass Accessories",
                "Strings",
                "Acoustic Guitar Strings"
            ]
        },
        "B0002E1NNC": {
            "title": "Elixir Strings 80/20 Bronze Acoustic Guitar Strings w POLYWEB Coating, Extra Light (.010-.047)",
            "avg_ratings": 4.533101045296167,
            "num_ratings": 287,
            "brand": "Elixir",
            "sub_categories": [
                "Musical Instruments",
                "Instrument Accessories",
                "Guitar & Bass Accessories",
                "Strings",
                "Acoustic Guitar Strings"
            ]
        },
        "B000XI6O2W": {
            "title": "Singing Machine SMM-205 Unidirectional Dynamic Microphone with 10 Ft. Cord",
            "avg_ratings": 3.6666666666666665,
            "num_ratings": 282,
            "brand": "Singing Machine",
            "sub_categories": [
                "Musical Instruments",
                "Microphones & Accessories",
                "Microphones",
                "Dynamic Microphones",
                "Vocal"
            ]
        },
        "B00XQFONF4": {
            "title": "Dragonpad USA 6\" Microphone Studio Pop Filter with Clamp - Pink/White",
            "avg_ratings": 4.07942238267148,
            "num_ratings": 277,
            "brand": "DragonPad USA",
            "sub_categories": [
                "Musical Instruments",
                "Microphones & Accessories",
                "Accessories",
                "Windscreens & Pop Filters"
            ]
        },
        "B0006NDF8A": {
            "title": "On-Stage XCG4 Black Tripod Guitar Stand, Single",
            "avg_ratings": 4.444444444444445,
            "num_ratings": 270,
            "brand": "OnStage",
            "sub_categories": [
                "Musical Instruments",
                "Instrument Accessories",
                "Guitar & Bass Accessories"
            ]
        },
        "B0007Y09VO": {
            "title": "D'Addario EJ17-B25 Phosphor Bronze Acoustic Guitar Strings, Medium, 13-56, 25 Bulk Sets",
            "avg_ratings": 4.584677419354839,
            "num_ratings": 248,
            "brand": "D'Addario",
            "sub_categories": [
                "Musical Instruments",
                "Instrument Accessories",
                "Guitar & Bass Accessories",
                "Strings",
                "Acoustic Guitar Strings"
            ]
        }
    },
    "May": {
        "B004XNK7AI": {
            "title": "Snark SN-5 Tuner for Guitar, Bass and Violin (Black)",
            "avg_ratings": 4.669064748201439,
            "num_ratings": 417,
            "brand": "Snark",
            "sub_categories": [
                "Musical Instruments",
                "Instrument Accessories",
                "Guitar & Bass Accessories",
                "Tuners"
            ]
        },
        "B00XQFONF4": {
            "title": "Dragonpad USA 6\" Microphone Studio Pop Filter with Clamp - Pink/White",
            "avg_ratings": 4.037790697674419,
            "num_ratings": 344,
            "brand": "DragonPad USA",
            "sub_categories": [
                "Musical Instruments",
                "Microphones & Accessories",
                "Accessories",
                "Windscreens & Pop Filters"
            ]
        },
        "B00DY1F2CS": {
            "title": "NEEWER Adjustable Microphone Suspension Boom Scissor Arm Stand, Max Load 1 KG Compact Mic Stand Made of Durable Steel for Radio Broadcasting Studio, Voice-Over Sound Studio, Stages, and TV Stations",
            "avg_ratings": 3.74294670846395,
            "num_ratings": 319,
            "brand": "Neewer",
            "sub_categories": [
                "Musical Instruments",
                "Microphones & Accessories",
                "Accessories",
                "Stands"
            ]
        },
        "B00IFOTSJW": {
            "title": "Snark SN1 Guitar Tuner (Blue)",
            "avg_ratings": 4.564285714285714,
            "num_ratings": 280,
            "brand": "Snark",
            "sub_categories": [
                "Musical Instruments",
                "Instrument Accessories",
                "Guitar & Bass Accessories",
                "Tuners"
            ]
        },
        "B000VSM4MS": {
            "title": "Crescent MG38-PK 38\" Acoustic Guitar Starter Package, PINK (Includes CrescentTM Digital E-Tuner)",
            "avg_ratings": 3.4962962962962965,
            "num_ratings": 270,
            "brand": "Crescent",
            "sub_categories": [
                "Musical Instruments",
                "Guitars",
                "Acoustic Guitars",
                "Steel-string Acoustics"
            ]
        },
        "B0002E1NWI": {
            "title": "Elixir Strings 80/20 Bronze Acoustic Guitar Strings w POLYWEB Coating, Light/Medium (.012-.056)",
            "avg_ratings": 4.665384615384616,
            "num_ratings": 260,
            "brand": "Elixir",
            "sub_categories": [
                "Musical Instruments",
                "Instrument Accessories",
                "Guitar & Bass Accessories",
                "Strings",
                "Acoustic Guitar Strings"
            ]
        },
        "B0002E1NNC": {
            "title": "Elixir Strings 80/20 Bronze Acoustic Guitar Strings w POLYWEB Coating, Extra Light (.010-.047)",
            "avg_ratings": 4.665384615384616,
            "num_ratings": 260,
            "brand": "Elixir",
            "sub_categories": [
                "Musical Instruments",
                "Instrument Accessories",
                "Guitar & Bass Accessories",
                "Strings",
                "Acoustic Guitar Strings"
            ]
        },
        "B000XI6O2W": {
            "title": "Singing Machine SMM-205 Unidirectional Dynamic Microphone with 10 Ft. Cord",
            "avg_ratings": 4.06,
            "num_ratings": 250,
            "brand": "Singing Machine",
            "sub_categories": [
                "Musical Instruments",
                "Microphones & Accessories",
                "Microphones",
                "Dynamic Microphones",
                "Vocal"
            ]
        },
        "B0007Y09VO": {
            "title": "D'Addario EJ17-B25 Phosphor Bronze Acoustic Guitar Strings, Medium, 13-56, 25 Bulk Sets",
            "avg_ratings": 4.70042194092827,
            "num_ratings": 237,
            "brand": "D'Addario",
            "sub_categories": [
                "Musical Instruments",
                "Instrument Accessories",
                "Guitar & Bass Accessories",
                "Strings",
                "Acoustic Guitar Strings"
            ]
        },
        "B0002H0A3S": {
            "title": "D'Addario EJ26 Phosphor Bronze Acoustic Guitar Strings, Custom Light, 11-52",
            "avg_ratings": 4.706382978723404,
            "num_ratings": 235,
            "brand": "D'Addario",
            "sub_categories": [
                "Musical Instruments",
                "Instrument Accessories",
                "Guitar & Bass Accessories",
                "Strings",
                "Acoustic Guitar Strings"
            ]
        }
    },
    "Jun": {
        "B004XNK7AI": {
            "title": "Snark SN-5 Tuner for Guitar, Bass and Violin (Black)",
            "avg_ratings": 4.631168831168831,
            "num_ratings": 385,
            "brand": "Snark",
            "sub_categories": [
                "Musical Instruments",
                "Instrument Accessories",
                "Guitar & Bass Accessories",
                "Tuners"
            ]
        },
        "B00XQFONF4": {
            "title": "Dragonpad USA 6\" Microphone Studio Pop Filter with Clamp - Pink/White",
            "avg_ratings": 4.046783625730995,
            "num_ratings": 342,
            "brand": "DragonPad USA",
            "sub_categories": [
                "Musical Instruments",
                "Microphones & Accessories",
                "Accessories",
                "Windscreens & Pop Filters"
            ]
        },
        "B00DY1F2CS": {
            "title": "NEEWER Adjustable Microphone Suspension Boom Scissor Arm Stand, Max Load 1 KG Compact Mic Stand Made of Durable Steel for Radio Broadcasting Studio, Voice-Over Sound Studio, Stages, and TV Stations",
            "avg_ratings": 3.589820359281437,
            "num_ratings": 334,
            "brand": "Neewer",
            "sub_categories": [
                "Musical Instruments",
                "Microphones & Accessories",
                "Accessories",
                "Stands"
            ]
        },
        "B00IFOTSJW": {
            "title": "Snark SN1 Guitar Tuner (Blue)",
            "avg_ratings": 4.581081081081081,
            "num_ratings": 296,
            "brand": "Snark",
            "sub_categories": [
                "Musical Instruments",
                "Instrument Accessories",
                "Guitar & Bass Accessories",
                "Tuners"
            ]
        },
        "B000VSM4MS": {
            "title": "Crescent MG38-PK 38\" Acoustic Guitar Starter Package, PINK (Includes CrescentTM Digital E-Tuner)",
            "avg_ratings": 3.3576642335766422,
            "num_ratings": 274,
            "brand": "Crescent",
            "sub_categories": [
                "Musical Instruments",
                "Guitars",
                "Acoustic Guitars",
                "Steel-string Acoustics"
            ]
        },
        "B0002E1NWI": {
            "title": "Elixir Strings 80/20 Bronze Acoustic Guitar Strings w POLYWEB Coating, Light/Medium (.012-.056)",
            "avg_ratings": 4.607287449392713,
            "num_ratings": 247,
            "brand": "Elixir",
            "sub_categories": [
                "Musical Instruments",
                "Instrument Accessories",
                "Guitar & Bass Accessories",
                "Strings",
                "Acoustic Guitar Strings"
            ]
        },
        "B0002E1NNC": {
            "title": "Elixir Strings 80/20 Bronze Acoustic Guitar Strings w POLYWEB Coating, Extra Light (.010-.047)",
            "avg_ratings": 4.607287449392713,
            "num_ratings": 247,
            "brand": "Elixir",
            "sub_categories": [
                "Musical Instruments",
                "Instrument Accessories",
                "Guitar & Bass Accessories",
                "Strings",
                "Acoustic Guitar Strings"
            ]
        },
        "B00IFHCOAE": {
            "title": "Snark SN2 Guitar Tuner",
            "avg_ratings": 4.567099567099567,
            "num_ratings": 231,
            "brand": "Snark",
            "sub_categories": [
                "Musical Instruments",
                "Instrument Accessories",
                "Guitar & Bass Accessories",
                "Tuners"
            ]
        },
        "B000VJJQUU": {
            "title": "CBI MLC LowZ XLR Male to XLR Female Microphone Cable, 20 Feet",
            "avg_ratings": 4.280701754385965,
            "num_ratings": 228,
            "brand": "CBI Cables",
            "sub_categories": [
                "Musical Instruments",
                "Live Sound & Stage",
                "Stage & Studio Cables",
                "Microphone Cables"
            ]
        },
        "B00063678K": {
            "title": "M-Audio SP-2 | Universal Sustain Pedal with Piano Style Action for Electronic Keyboards",
            "avg_ratings": 4.585,
            "num_ratings": 200,
            "brand": "M-Audio",
            "sub_categories": [
                "Musical Instruments",
                "Instrument Accessories",
                "Keyboard Accessories",
                "Pedals & Footswitches"
            ]
        }
    },
    "Jul": {
        "B004XNK7AI": {
            "title": "Snark SN-5 Tuner for Guitar, Bass and Violin (Black)",
            "avg_ratings": 4.639506172839506,
            "num_ratings": 405,
            "brand": "Snark",
            "sub_categories": [
                "Musical Instruments",
                "Instrument Accessories",
                "Guitar & Bass Accessories",
                "Tuners"
            ]
        },
        "B00DY1F2CS": {
            "title": "NEEWER Adjustable Microphone Suspension Boom Scissor Arm Stand, Max Load 1 KG Compact Mic Stand Made of Durable Steel for Radio Broadcasting Studio, Voice-Over Sound Studio, Stages, and TV Stations",
            "avg_ratings": 3.754601226993865,
            "num_ratings": 326,
            "brand": "Neewer",
            "sub_categories": [
                "Musical Instruments",
                "Microphones & Accessories",
                "Accessories",
                "Stands"
            ]
        },
        "B00XQFONF4": {
            "title": "Dragonpad USA 6\" Microphone Studio Pop Filter with Clamp - Pink/White",
            "avg_ratings": 4.091803278688524,
            "num_ratings": 305,
            "brand": "DragonPad USA",
            "sub_categories": [
                "Musical Instruments",
                "Microphones & Accessories",
                "Accessories",
                "Windscreens & Pop Filters"
            ]
        },
        "B0002E1NWI": {
            "title": "Elixir Strings 80/20 Bronze Acoustic Guitar Strings w POLYWEB Coating, Light/Medium (.012-.056)",
            "avg_ratings": 4.660839160839161,
            "num_ratings": 286,
            "brand": "Elixir",
            "sub_categories": [
                "Musical Instruments",
                "Instrument Accessories",
                "Guitar & Bass Accessories",
                "Strings",
                "Acoustic Guitar Strings"
            ]
        },
        "B0002E1NNC": {
            "title": "Elixir Strings 80/20 Bronze Acoustic Guitar Strings w POLYWEB Coating, Extra Light (.010-.047)",
            "avg_ratings": 4.660839160839161,
            "num_ratings": 286,
            "brand": "Elixir",
            "sub_categories": [
                "Musical Instruments",
                "Instrument Accessories",
                "Guitar & Bass Accessories",
                "Strings",
                "Acoustic Guitar Strings"
            ]
        },
        "B00IFOTSJW": {
            "title": "Snark SN1 Guitar Tuner (Blue)",
            "avg_ratings": 4.640845070422535,
            "num_ratings": 284,
            "brand": "Snark",
            "sub_categories": [
                "Musical Instruments",
                "Instrument Accessories",
                "Guitar & Bass Accessories",
                "Tuners"
            ]
        },
        "B000VSM4MS": {
            "title": "Crescent MG38-PK 38\" Acoustic Guitar Starter Package, PINK (Includes CrescentTM Digital E-Tuner)",
            "avg_ratings": 3.1954887218045114,
            "num_ratings": 266,
            "brand": "Crescent",
            "sub_categories": [
                "Musical Instruments",
                "Guitars",
                "Acoustic Guitars",
                "Steel-string Acoustics"
            ]
        },
        "B00SNBCBGE": {
            "title": "ION Audio Tailgater (iPA77) | Portable Bluetooth PA Speaker with Mic, AM/FM Radio, and USB Charge Port",
            "avg_ratings": 4.212355212355212,
            "num_ratings": 259,
            "brand": "ION Audio",
            "sub_categories": [
                "Musical Instruments",
                "Live Sound & Stage",
                "PA Systems"
            ]
        },
        "B00O4L3F9E": {
            "title": "KLIQ UberTuner - Clip-On Tuner for All Instruments - with Guitar, Bass, Violin, Ukulele & Chromatic Tuning Modes",
            "avg_ratings": 4.724696356275303,
            "num_ratings": 247,
            "brand": "KLIQ Music Gear",
            "sub_categories": [
                "Musical Instruments",
                "Instrument Accessories",
                "General Accessories",
                "Tuning"
            ]
        },
        "B0002E1G5C": {
            "title": "DAddario Accessories Pro-Winder Guitar String Winder and Cutter  All-In-1 Restringing Tool  Includes Clippers, Bridge Pin Puller, Peg Winder  Designed to Fit Most Guitars",
            "avg_ratings": 4.279661016949152,
            "num_ratings": 236,
            "brand": "D'Addario Accessories",
            "sub_categories": [
                "Musical Instruments",
                "Instrument Accessories",
                "Guitar & Bass Accessories",
                "Tools"
            ]
        }
    },
    "Aug": {
        "B004XNK7AI": {
            "title": "Snark SN-5 Tuner for Guitar, Bass and Violin (Black)",
            "avg_ratings": 4.666666666666667,
            "num_ratings": 399,
            "brand": "Snark",
            "sub_categories": [
                "Musical Instruments",
                "Instrument Accessories",
                "Guitar & Bass Accessories",
                "Tuners"
            ]
        },
        "B00DY1F2CS": {
            "title": "NEEWER Adjustable Microphone Suspension Boom Scissor Arm Stand, Max Load 1 KG Compact Mic Stand Made of Durable Steel for Radio Broadcasting Studio, Voice-Over Sound Studio, Stages, and TV Stations",
            "avg_ratings": 3.8584070796460175,
            "num_ratings": 339,
            "brand": "Neewer",
            "sub_categories": [
                "Musical Instruments",
                "Microphones & Accessories",
                "Accessories",
                "Stands"
            ]
        },
        "B000VSM4MS": {
            "title": "Crescent MG38-PK 38\" Acoustic Guitar Starter Package, PINK (Includes CrescentTM Digital E-Tuner)",
            "avg_ratings": 3.5625,
            "num_ratings": 320,
            "brand": "Crescent",
            "sub_categories": [
                "Musical Instruments",
                "Guitars",
                "Acoustic Guitars",
                "Steel-string Acoustics"
            ]
        },
        "B00XQFONF4": {
            "title": "Dragonpad USA 6\" Microphone Studio Pop Filter with Clamp - Pink/White",
            "avg_ratings": 3.996742671009772,
            "num_ratings": 307,
            "brand": "DragonPad USA",
            "sub_categories": [
                "Musical Instruments",
                "Microphones & Accessories",
                "Accessories",
                "Windscreens & Pop Filters"
            ]
        },
        "B0002E1NWI": {
            "title": "Elixir Strings 80/20 Bronze Acoustic Guitar Strings w POLYWEB Coating, Light/Medium (.012-.056)",
            "avg_ratings": 4.5215946843853825,
            "num_ratings": 301,
            "brand": "Elixir",
            "sub_categories": [
                "Musical Instruments",
                "Instrument Accessories",
                "Guitar & Bass Accessories",
                "Strings",
                "Acoustic Guitar Strings"
            ]
        },
        "B0002E1NNC": {
            "title": "Elixir Strings 80/20 Bronze Acoustic Guitar Strings w POLYWEB Coating, Extra Light (.010-.047)",
            "avg_ratings": 4.5215946843853825,
            "num_ratings": 301,
            "brand": "Elixir",
            "sub_categories": [
                "Musical Instruments",
                "Instrument Accessories",
                "Guitar & Bass Accessories",
                "Strings",
                "Acoustic Guitar Strings"
            ]
        },
        "B00IFOTSJW": {
            "title": "Snark SN1 Guitar Tuner (Blue)",
            "avg_ratings": 4.57,
            "num_ratings": 300,
            "brand": "Snark",
            "sub_categories": [
                "Musical Instruments",
                "Instrument Accessories",
                "Guitar & Bass Accessories",
                "Tuners"
            ]
        },
        "B00063678K": {
            "title": "M-Audio SP-2 | Universal Sustain Pedal with Piano Style Action for Electronic Keyboards",
            "avg_ratings": 4.516806722689076,
            "num_ratings": 238,
            "brand": "M-Audio",
            "sub_categories": [
                "Musical Instruments",
                "Instrument Accessories",
                "Keyboard Accessories",
                "Pedals & Footswitches"
            ]
        },
        "B0007Y09VO": {
            "title": "D'Addario EJ17-B25 Phosphor Bronze Acoustic Guitar Strings, Medium, 13-56, 25 Bulk Sets",
            "avg_ratings": 4.636752136752137,
            "num_ratings": 234,
            "brand": "D'Addario",
            "sub_categories": [
                "Musical Instruments",
                "Instrument Accessories",
                "Guitar & Bass Accessories",
                "Strings",
                "Acoustic Guitar Strings"
            ]
        },
        "B0002H0A3S": {
            "title": "D'Addario EJ26 Phosphor Bronze Acoustic Guitar Strings, Custom Light, 11-52",
            "avg_ratings": 4.636752136752137,
            "num_ratings": 234,
            "brand": "D'Addario",
            "sub_categories": [
                "Musical Instruments",
                "Instrument Accessories",
                "Guitar & Bass Accessories",
                "Strings",
                "Acoustic Guitar Strings"
            ]
        }
    },
    "Sep": {
        "B004XNK7AI": {
            "title": "Snark SN-5 Tuner for Guitar, Bass and Violin (Black)",
            "avg_ratings": 4.613293051359516,
            "num_ratings": 331,
            "brand": "Snark",
            "sub_categories": [
                "Musical Instruments",
                "Instrument Accessories",
                "Guitar & Bass Accessories",
                "Tuners"
            ]
        },
        "B000VSM4MS": {
            "title": "Crescent MG38-PK 38\" Acoustic Guitar Starter Package, PINK (Includes CrescentTM Digital E-Tuner)",
            "avg_ratings": 3.7025316455696204,
            "num_ratings": 316,
            "brand": "Crescent",
            "sub_categories": [
                "Musical Instruments",
                "Guitars",
                "Acoustic Guitars",
                "Steel-string Acoustics"
            ]
        },
        "B0002E1NWI": {
            "title": "Elixir Strings 80/20 Bronze Acoustic Guitar Strings w POLYWEB Coating, Light/Medium (.012-.056)",
            "avg_ratings": 4.6050955414012735,
            "num_ratings": 314,
            "brand": "Elixir",
            "sub_categories": [
                "Musical Instruments",
                "Instrument Accessories",
                "Guitar & Bass Accessories",
                "Strings",
                "Acoustic Guitar Strings"
            ]
        },
        "B0002E1NNC": {
            "title": "Elixir Strings 80/20 Bronze Acoustic Guitar Strings w POLYWEB Coating, Extra Light (.010-.047)",
            "avg_ratings": 4.6050955414012735,
            "num_ratings": 314,
            "brand": "Elixir",
            "sub_categories": [
                "Musical Instruments",
                "Instrument Accessories",
                "Guitar & Bass Accessories",
                "Strings",
                "Acoustic Guitar Strings"
            ]
        },
        "B00DY1F2CS": {
            "title": "NEEWER Adjustable Microphone Suspension Boom Scissor Arm Stand, Max Load 1 KG Compact Mic Stand Made of Durable Steel for Radio Broadcasting Studio, Voice-Over Sound Studio, Stages, and TV Stations",
            "avg_ratings": 3.8705882352941177,
            "num_ratings": 255,
            "brand": "Neewer",
            "sub_categories": [
                "Musical Instruments",
                "Microphones & Accessories",
                "Accessories",
                "Stands"
            ]
        },
        "B002026DR0": {
            "title": "Mendini 4/4 MV300 Solid Wood Satin Antique Violin with Hard Case, Shoulder Rest, Bow, Rosin and Extra Strings (Full Size)",
            "avg_ratings": 3.372549019607843,
            "num_ratings": 255,
            "brand": "Mendini",
            "sub_categories": [
                "Musical Instruments",
                "Band & Orchestra",
                "Orchestral Strings",
                "Violins",
                "Acoustic Violins"
            ]
        },
        "B00IFOTSJW": {
            "title": "Snark SN1 Guitar Tuner (Blue)",
            "avg_ratings": 4.434262948207171,
            "num_ratings": 251,
            "brand": "Snark",
            "sub_categories": [
                "Musical Instruments",
                "Instrument Accessories",
                "Guitar & Bass Accessories",
                "Tuners"
            ]
        },
        "B00XQFONF4": {
            "title": "Dragonpad USA 6\" Microphone Studio Pop Filter with Clamp - Pink/White",
            "avg_ratings": 4.069105691056911,
            "num_ratings": 246,
            "brand": "DragonPad USA",
            "sub_categories": [
                "Musical Instruments",
                "Microphones & Accessories",
                "Accessories",
                "Windscreens & Pop Filters"
            ]
        },
        "B0006NDF8A": {
            "title": "On-Stage XCG4 Black Tripod Guitar Stand, Single",
            "avg_ratings": 4.3954545454545455,
            "num_ratings": 220,
            "brand": "OnStage",
            "sub_categories": [
                "Musical Instruments",
                "Instrument Accessories",
                "Guitar & Bass Accessories"
            ]
        },
        "B00063678K": {
            "title": "M-Audio SP-2 | Universal Sustain Pedal with Piano Style Action for Electronic Keyboards",
            "avg_ratings": 4.4575471698113205,
            "num_ratings": 212,
            "brand": "M-Audio",
            "sub_categories": [
                "Musical Instruments",
                "Instrument Accessories",
                "Keyboard Accessories",
                "Pedals & Footswitches"
            ]
        }
    },
    "Oct": {
        "B002026DR0": {
            "title": "Mendini 4/4 MV300 Solid Wood Satin Antique Violin with Hard Case, Shoulder Rest, Bow, Rosin and Extra Strings (Full Size)",
            "avg_ratings": 3.527536231884058,
            "num_ratings": 345,
            "brand": "Mendini",
            "sub_categories": [
                "Musical Instruments",
                "Band & Orchestra",
                "Orchestral Strings",
                "Violins",
                "Acoustic Violins"
            ]
        },
        "B000VSM4MS": {
            "title": "Crescent MG38-PK 38\" Acoustic Guitar Starter Package, PINK (Includes CrescentTM Digital E-Tuner)",
            "avg_ratings": 3.5542168674698793,
            "num_ratings": 332,
            "brand": "Crescent",
            "sub_categories": [
                "Musical Instruments",
                "Guitars",
                "Acoustic Guitars",
                "Steel-string Acoustics"
            ]
        },
        "B00KUC2INU": {
            "title": "Roxant Pro Mini LED Strobe Light with 24 Super Bright LEDs With Variable Speed Control - ROX-ST1",
            "avg_ratings": 4.82484076433121,
            "num_ratings": 314,
            "brand": "Roxant",
            "sub_categories": [
                "Musical Instruments",
                "Live Sound & Stage",
                "Lighting Equipment & Accessories",
                "Laser & Strobe Effects",
                "Strobe Effects"
            ]
        },
        "B004XNK7AI": {
            "title": "Snark SN-5 Tuner for Guitar, Bass and Violin (Black)",
            "avg_ratings": 4.721476510067114,
            "num_ratings": 298,
            "brand": "Snark",
            "sub_categories": [
                "Musical Instruments",
                "Instrument Accessories",
                "Guitar & Bass Accessories",
                "Tuners"
            ]
        },
        "B00DY1F2CS": {
            "title": "NEEWER Adjustable Microphone Suspension Boom Scissor Arm Stand, Max Load 1 KG Compact Mic Stand Made of Durable Steel for Radio Broadcasting Studio, Voice-Over Sound Studio, Stages, and TV Stations",
            "avg_ratings": 3.8461538461538463,
            "num_ratings": 273,
            "brand": "Neewer",
            "sub_categories": [
                "Musical Instruments",
                "Microphones & Accessories",
                "Accessories",
                "Stands"
            ]
        },
        "B0002E1NWI": {
            "title": "Elixir Strings 80/20 Bronze Acoustic Guitar Strings w POLYWEB Coating, Light/Medium (.012-.056)",
            "avg_ratings": 4.617647058823529,
            "num_ratings": 272,
            "brand": "Elixir",
            "sub_categories": [
                "Musical Instruments",
                "Instrument Accessories",
                "Guitar & Bass Accessories",
                "Strings",
                "Acoustic Guitar Strings"
            ]
        },
        "B0002E1NNC": {
            "title": "Elixir Strings 80/20 Bronze Acoustic Guitar Strings w POLYWEB Coating, Extra Light (.010-.047)",
            "avg_ratings": 4.617647058823529,
            "num_ratings": 272,
            "brand": "Elixir",
            "sub_categories": [
                "Musical Instruments",
                "Instrument Accessories",
                "Guitar & Bass Accessories",
                "Strings",
                "Acoustic Guitar Strings"
            ]
        },
        "B00IFOTSJW": {
            "title": "Snark SN1 Guitar Tuner (Blue)",
            "avg_ratings": 4.4148148148148145,
            "num_ratings": 270,
            "brand": "Snark",
            "sub_categories": [
                "Musical Instruments",
                "Instrument Accessories",
                "Guitar & Bass Accessories",
                "Tuners"
            ]
        },
        "B00XQFONF4": {
            "title": "Dragonpad USA 6\" Microphone Studio Pop Filter with Clamp - Pink/White",
            "avg_ratings": 4.096,
            "num_ratings": 250,
            "brand": "DragonPad USA",
            "sub_categories": [
                "Musical Instruments",
                "Microphones & Accessories",
                "Accessories",
                "Windscreens & Pop Filters"
            ]
        },
        "B0006NDF8A": {
            "title": "On-Stage XCG4 Black Tripod Guitar Stand, Single",
            "avg_ratings": 4.3125,
            "num_ratings": 224,
            "brand": "OnStage",
            "sub_categories": [
                "Musical Instruments",
                "Instrument Accessories",
                "Guitar & Bass Accessories"
            ]
        }
    },
    "Nov": {
        "B004XNK7AI": {
            "title": "Snark SN-5 Tuner for Guitar, Bass and Violin (Black)",
            "avg_ratings": 4.679127725856698,
            "num_ratings": 321,
            "brand": "Snark",
            "sub_categories": [
                "Musical Instruments",
                "Instrument Accessories",
                "Guitar & Bass Accessories",
                "Tuners"
            ]
        },
        "B000VSM4MS": {
            "title": "Crescent MG38-PK 38\" Acoustic Guitar Starter Package, PINK (Includes CrescentTM Digital E-Tuner)",
            "avg_ratings": 3.56875,
            "num_ratings": 320,
            "brand": "Crescent",
            "sub_categories": [
                "Musical Instruments",
                "Guitars",
                "Acoustic Guitars",
                "Steel-string Acoustics"
            ]
        },
        "B0002E1NWI": {
            "title": "Elixir Strings 80/20 Bronze Acoustic Guitar Strings w POLYWEB Coating, Light/Medium (.012-.056)",
            "avg_ratings": 4.597269624573379,
            "num_ratings": 293,
            "brand": "Elixir",
            "sub_categories": [
                "Musical Instruments",
                "Instrument Accessories",
                "Guitar & Bass Accessories",
                "Strings",
                "Acoustic Guitar Strings"
            ]
        },
        "B0002E1NNC": {
            "title": "Elixir Strings 80/20 Bronze Acoustic Guitar Strings w POLYWEB Coating, Extra Light (.010-.047)",
            "avg_ratings": 4.597269624573379,
            "num_ratings": 293,
            "brand": "Elixir",
            "sub_categories": [
                "Musical Instruments",
                "Instrument Accessories",
                "Guitar & Bass Accessories",
                "Strings",
                "Acoustic Guitar Strings"
            ]
        },
        "B00DY1F2CS": {
            "title": "NEEWER Adjustable Microphone Suspension Boom Scissor Arm Stand, Max Load 1 KG Compact Mic Stand Made of Durable Steel for Radio Broadcasting Studio, Voice-Over Sound Studio, Stages, and TV Stations",
            "avg_ratings": 3.7857142857142856,
            "num_ratings": 280,
            "brand": "Neewer",
            "sub_categories": [
                "Musical Instruments",
                "Microphones & Accessories",
                "Accessories",
                "Stands"
            ]
        },
        "B00XQFONF4": {
            "title": "Dragonpad USA 6\" Microphone Studio Pop Filter with Clamp - Pink/White",
            "avg_ratings": 4.0359712230215825,
            "num_ratings": 278,
            "brand": "DragonPad USA",
            "sub_categories": [
                "Musical Instruments",
                "Microphones & Accessories",
                "Accessories",
                "Windscreens & Pop Filters"
            ]
        },
        "B00IFOTSJW": {
            "title": "Snark SN1 Guitar Tuner (Blue)",
            "avg_ratings": 4.658088235294118,
            "num_ratings": 272,
            "brand": "Snark",
            "sub_categories": [
                "Musical Instruments",
                "Instrument Accessories",
                "Guitar & Bass Accessories",
                "Tuners"
            ]
        },
        "B002026DR0": {
            "title": "Mendini 4/4 MV300 Solid Wood Satin Antique Violin with Hard Case, Shoulder Rest, Bow, Rosin and Extra Strings (Full Size)",
            "avg_ratings": 3.531496062992126,
            "num_ratings": 254,
            "brand": "Mendini",
            "sub_categories": [
                "Musical Instruments",
                "Band & Orchestra",
                "Orchestral Strings",
                "Violins",
                "Acoustic Violins"
            ]
        },
        "B0007Y09VO": {
            "title": "D'Addario EJ17-B25 Phosphor Bronze Acoustic Guitar Strings, Medium, 13-56, 25 Bulk Sets",
            "avg_ratings": 4.702586206896552,
            "num_ratings": 232,
            "brand": "D'Addario",
            "sub_categories": [
                "Musical Instruments",
                "Instrument Accessories",
                "Guitar & Bass Accessories",
                "Strings",
                "Acoustic Guitar Strings"
            ]
        },
        "B0002H0A3S": {
            "title": "D'Addario EJ26 Phosphor Bronze Acoustic Guitar Strings, Custom Light, 11-52",
            "avg_ratings": 4.702586206896552,
            "num_ratings": 232,
            "brand": "D'Addario",
            "sub_categories": [
                "Musical Instruments",
                "Instrument Accessories",
                "Guitar & Bass Accessories",
                "Strings",
                "Acoustic Guitar Strings"
            ]
        }
    },
    "Dec": {
        "B000VSM4MS": {
            "title": "Crescent MG38-PK 38\" Acoustic Guitar Starter Package, PINK (Includes CrescentTM Digital E-Tuner)",
            "avg_ratings": 3.4202127659574466,
            "num_ratings": 752,
            "brand": "Crescent",
            "sub_categories": [
                "Musical Instruments",
                "Guitars",
                "Acoustic Guitars",
                "Steel-string Acoustics"
            ]
        },
        "B000XI6O2W": {
            "title": "Singing Machine SMM-205 Unidirectional Dynamic Microphone with 10 Ft. Cord",
            "avg_ratings": 3.7929824561403507,
            "num_ratings": 570,
            "brand": "Singing Machine",
            "sub_categories": [
                "Musical Instruments",
                "Microphones & Accessories",
                "Microphones",
                "Dynamic Microphones",
                "Vocal"
            ]
        },
        "B00IFOTSJW": {
            "title": "Snark SN1 Guitar Tuner (Blue)",
            "avg_ratings": 4.608349900596422,
            "num_ratings": 503,
            "brand": "Snark",
            "sub_categories": [
                "Musical Instruments",
                "Instrument Accessories",
                "Guitar & Bass Accessories",
                "Tuners"
            ]
        },
        "B004XNK7AI": {
            "title": "Snark SN-5 Tuner for Guitar, Bass and Violin (Black)",
            "avg_ratings": 4.673267326732673,
            "num_ratings": 404,
            "brand": "Snark",
            "sub_categories": [
                "Musical Instruments",
                "Instrument Accessories",
                "Guitar & Bass Accessories",
                "Tuners"
            ]
        },
        "B002026DR0": {
            "title": "Mendini 4/4 MV300 Solid Wood Satin Antique Violin with Hard Case, Shoulder Rest, Bow, Rosin and Extra Strings (Full Size)",
            "avg_ratings": 3.3821138211382116,
            "num_ratings": 369,
            "brand": "Mendini",
            "sub_categories": [
                "Musical Instruments",
                "Band & Orchestra",
                "Orchestral Strings",
                "Violins",
                "Acoustic Violins"
            ]
        },
        "B00XQFONF4": {
            "title": "Dragonpad USA 6\" Microphone Studio Pop Filter with Clamp - Pink/White",
            "avg_ratings": 4.095774647887324,
            "num_ratings": 355,
            "brand": "DragonPad USA",
            "sub_categories": [
                "Musical Instruments",
                "Microphones & Accessories",
                "Accessories",
                "Windscreens & Pop Filters"
            ]
        },
        "B00DY1F2CS": {
            "title": "NEEWER Adjustable Microphone Suspension Boom Scissor Arm Stand, Max Load 1 KG Compact Mic Stand Made of Durable Steel for Radio Broadcasting Studio, Voice-Over Sound Studio, Stages, and TV Stations",
            "avg_ratings": 3.7485714285714287,
            "num_ratings": 350,
            "brand": "Neewer",
            "sub_categories": [
                "Musical Instruments",
                "Microphones & Accessories",
                "Accessories",
                "Stands"
            ]
        },
        "B0006NDF8A": {
            "title": "On-Stage XCG4 Black Tripod Guitar Stand, Single",
            "avg_ratings": 4.303724928366762,
            "num_ratings": 349,
            "brand": "OnStage",
            "sub_categories": [
                "Musical Instruments",
                "Instrument Accessories",
                "Guitar & Bass Accessories"
            ]
        },
        "B0002E1NWI": {
            "title": "Elixir Strings 80/20 Bronze Acoustic Guitar Strings w POLYWEB Coating, Light/Medium (.012-.056)",
            "avg_ratings": 4.648318042813456,
            "num_ratings": 327,
            "brand": "Elixir",
            "sub_categories": [
                "Musical Instruments",
                "Instrument Accessories",
                "Guitar & Bass Accessories",
                "Strings",
                "Acoustic Guitar Strings"
            ]
        },
        "B0002E1NNC": {
            "title": "Elixir Strings 80/20 Bronze Acoustic Guitar Strings w POLYWEB Coating, Extra Light (.010-.047)",
            "avg_ratings": 4.648318042813456,
            "num_ratings": 327,
            "brand": "Elixir",
            "sub_categories": [
                "Musical Instruments",
                "Instrument Accessories",
                "Guitar & Bass Accessories",
                "Strings",
                "Acoustic Guitar Strings"
            ]
        }
    }
}