{
    "Jan": {
        "B01H3KUG9O": {
            "title": "Love Remains",
            "avg_ratings": 5.0,
            "num_ratings": 31,
            "brand": "Hillary Scott and the Scott Family",
            "sub_categories": [
                "CDs & Vinyl",
                "Country"
            ]
        },
        "B01855N1KC": {
            "title": "Ghostlights",
            "avg_ratings": 5.0,
            "num_ratings": 24,
            "brand": "Avantasia",
            "sub_categories": [
                "CDs & Vinyl",
                "Metal"
            ]
        },
        "B01843CZZC": {
            "title": "Hymns That Are Important To Us",
            "avg_ratings": 5.0,
            "num_ratings": 29,
            "brand": "Joey + Rory",
            "sub_categories": [
                "CDs & Vinyl",
                "Christian",
                "Pop & Contemporary"
            ]
        },
        "B015UDEJSA": {
            "title": "A Live Worship Experience",
            "avg_ratings": 5.0,
            "num_ratings": 16,
            "brand": "Casting Crowns",
            "sub_categories": [
                "CDs & Vinyl",
                "Christian",
                "Pop & Contemporary"
            ]
        },
        "B014V01J0Y": {
            "title": "Mothership",
            "avg_ratings": 5.0,
            "num_ratings": 28,
            "brand": "Led Zeppelin",
            "sub_categories": [
                "CDs & Vinyl",
                "Pop"
            ]
        },
        "B00OMBJYR8": {
            "title": "Everlasting",
            "avg_ratings": 5.0,
            "num_ratings": 15,
            "brand": "Collin Raye",
            "sub_categories": [
                "CDs & Vinyl",
                "Country"
            ]
        },
        "B00NFSM45S": {
            "title": "Rise",
            "avg_ratings": 5.0,
            "num_ratings": 16,
            "brand": "Trip Lee",
            "sub_categories": [
                "CDs & Vinyl",
                "Rap & Hip-Hop",
                "Pop Rap"
            ]
        },
        "B00JXETVRC": {
            "title": "Redeemer of Souls",
            "avg_ratings": 5.0,
            "num_ratings": 18,
            "brand": "Judas Priest",
            "sub_categories": [
                "CDs & Vinyl",
                "Metal",
                "Pop Metal"
            ]
        },
        "B00IJBAYVW": {
            "title": "Sovereign",
            "avg_ratings": 5.0,
            "num_ratings": 16,
            "brand": "Michael W. Smith",
            "sub_categories": [
                "CDs & Vinyl",
                "Christian",
                "Pop & Contemporary"
            ]
        },
        "B00HQRYJE8": {
            "title": "Riser",
            "avg_ratings": 5.0,
            "num_ratings": 18,
            "brand": "Dierks Bentley",
            "sub_categories": [
                "CDs & Vinyl",
                "Country",
                "Today's Country"
            ]
        }
    },
    "Feb": {
        "B01BIZRJQS": {
            "title": "Echoes",
            "avg_ratings": 5.0,
            "num_ratings": 23,
            "brand": "Byrne & Kelly",
            "sub_categories": [
                "CDs & Vinyl",
                "World Music"
            ]
        },
        "B0186QBZA8": {
            "title": "Most Beautiful Moments in Life Part 2",
            "avg_ratings": 5.0,
            "num_ratings": 16,
            "brand": "BTS",
            "sub_categories": [
                "CDs & Vinyl",
                "Pop"
            ]
        },
        "B0161H1K8G": {
            "title": "Nightbird",
            "avg_ratings": 5.0,
            "num_ratings": 18,
            "brand": "Eva Cassidy",
            "sub_categories": [
                "CDs & Vinyl",
                "Pop"
            ]
        },
        "B015UDEJSA": {
            "title": "A Live Worship Experience",
            "avg_ratings": 5.0,
            "num_ratings": 24,
            "brand": "Casting Crowns",
            "sub_categories": [
                "CDs & Vinyl",
                "Christian",
                "Pop & Contemporary"
            ]
        },
        "B014L2YF26": {
            "title": "KIDZ BOP 30",
            "avg_ratings": 5.0,
            "num_ratings": 17,
            "brand": "KIDZ BOP Kids",
            "sub_categories": [
                "CDs & Vinyl",
                "Children's Music"
            ]
        },
        "B00TU29LS6": {
            "title": "Under One Sky",
            "avg_ratings": 5.0,
            "num_ratings": 15,
            "brand": "The Tenors",
            "sub_categories": [
                "CDs & Vinyl",
                "Classical",
                "Symphonies"
            ]
        },
        "B00QTVK8TW": {
            "title": "I AM THEY",
            "avg_ratings": 5.0,
            "num_ratings": 16,
            "brand": "I AM THEY",
            "sub_categories": [
                "CDs & Vinyl",
                "Christian",
                "Pop & Contemporary"
            ]
        },
        "B00NM73MF8": {
            "title": "Holiday Symphony",
            "avg_ratings": 5.0,
            "num_ratings": 17,
            "brand": "Celtic Thunder",
            "sub_categories": [
                "CDs & Vinyl",
                "Holiday & Wedding"
            ]
        },
        "B00L47E6IA": {
            "title": "Step Back",
            "avg_ratings": 5.0,
            "num_ratings": 17,
            "brand": "Johnny Winter",
            "sub_categories": [
                "CDs & Vinyl",
                "Rock",
                "Blues Rock"
            ]
        },
        "B00K98J1E4": {
            "title": "Country Classics: A Tapestry Of Our Musical Heritage",
            "avg_ratings": 5.0,
            "num_ratings": 28,
            "brand": "Joey + Rory",
            "sub_categories": [
                "CDs & Vinyl",
                "Christian",
                "Pop & Contemporary"
            ]
        }
    },
    "Mar": {
        "B01F8ZVA0U": {
            "title": "Of Dirt And Grace - Live From The Land Live In Jerusalem/2016",
            "avg_ratings": 5.0,
            "num_ratings": 19,
            "brand": "Hillsong UNITED",
            "sub_categories": [
                "CDs & Vinyl",
                "Christian",
                "Pop & Contemporary"
            ]
        },
        "B01C8QG7VO": {
            "title": "Therapy Session",
            "avg_ratings": 5.0,
            "num_ratings": 17,
            "brand": "NF",
            "sub_categories": [
                "CDs & Vinyl",
                "Christian",
                "Rap & Hip-Hop"
            ]
        },
        "B01BWI22HC": {
            "title": "Battle Cry",
            "avg_ratings": 5.0,
            "num_ratings": 15,
            "brand": "Judas Priest",
            "sub_categories": [
                "CDs & Vinyl",
                "Pop"
            ]
        },
        "B01BIZRJQS": {
            "title": "Echoes",
            "avg_ratings": 5.0,
            "num_ratings": 29,
            "brand": "Byrne & Kelly",
            "sub_categories": [
                "CDs & Vinyl",
                "World Music"
            ]
        },
        "B01AEOM5D6": {
            "title": "Right Here",
            "avg_ratings": 5.0,
            "num_ratings": 19,
            "brand": "Charles Billingsley",
            "sub_categories": [
                "CDs & Vinyl",
                "Christian",
                "Pop & Contemporary"
            ]
        },
        "B018RZ7TJO": {
            "title": "The Hunchback of Notre Dame Studio Cast Recording",
            "avg_ratings": 5.0,
            "num_ratings": 20,
            "brand": "Various Artists",
            "sub_categories": [
                "CDs & Vinyl",
                "Broadway & Vocalists",
                "Musicals"
            ]
        },
        "B017JJRAJ8": {
            "title": "My Wild West",
            "avg_ratings": 5.0,
            "num_ratings": 15,
            "brand": "Lissie",
            "sub_categories": [
                "CDs & Vinyl",
                "Pop"
            ]
        },
        "B014V01J0Y": {
            "title": "Mothership",
            "avg_ratings": 5.0,
            "num_ratings": 20,
            "brand": "Led Zeppelin",
            "sub_categories": [
                "CDs & Vinyl",
                "Pop"
            ]
        },
        "B0148RIR96": {
            "title": "Dopamine",
            "avg_ratings": 5.0,
            "num_ratings": 20,
            "brand": "BRNS",
            "sub_categories": [
                "CDs & Vinyl",
                "Pop"
            ]
        },
        "B00X0UUFI4": {
            "title": "35 Biggest Hits",
            "avg_ratings": 5.0,
            "num_ratings": 17,
            "brand": "Hank Williams Jr.",
            "sub_categories": [
                "CDs & Vinyl",
                "Country"
            ]
        }
    },
    "Apr": {
        "B01BIZRJQS": {
            "title": "Echoes",
            "avg_ratings": 5.0,
            "num_ratings": 22,
            "brand": "Byrne & Kelly",
            "sub_categories": [
                "CDs & Vinyl",
                "World Music"
            ]
        },
        "B01BFZN0IW": {
            "title": "A Worshipper's Heart",
            "avg_ratings": 5.0,
            "num_ratings": 27,
            "brand": "Todd Dulaney",
            "sub_categories": [
                "CDs & Vinyl",
                "Pop"
            ]
        },
        "B017IXVSJS": {
            "title": "Here As In Heaven",
            "avg_ratings": 5.0,
            "num_ratings": 17,
            "brand": "Elevation Worship",
            "sub_categories": [
                "CDs & Vinyl",
                "Christian",
                "Pop & Contemporary"
            ]
        },
        "B015O42URC": {
            "title": "Losing My Religion",
            "avg_ratings": 5.0,
            "num_ratings": 19,
            "brand": "Kirk Franklin",
            "sub_categories": [
                "CDs & Vinyl",
                "Christian",
                "Pop & Contemporary"
            ]
        },
        "B0128GGONU": {
            "title": "WOW Hits 2016",
            "avg_ratings": 5.0,
            "num_ratings": 24,
            "brand": "Various Artists",
            "sub_categories": [
                "CDs & Vinyl",
                "Pop"
            ]
        },
        "B00UKC266Y": {
            "title": "The Calming Collection - Calm Mom, Calm Dad, Calm Child: Keeping Your Cool With Your Children, Your Family, and Everyone Else in Your Life",
            "avg_ratings": 5.0,
            "num_ratings": 16,
            "brand": "Roberta Shapiro",
            "sub_categories": [
                "CDs & Vinyl",
                "New Age",
                "Relaxation"
            ]
        },
        "B00TEQMJSC": {
            "title": "Extermination extra Tracks",
            "avg_ratings": 5.0,
            "num_ratings": 35,
            "brand": "Raven",
            "sub_categories": [
                "CDs & Vinyl",
                "Pop"
            ]
        },
        "B00SJ9TY9C": {
            "title": "Diamonds",
            "avg_ratings": 5.0,
            "num_ratings": 19,
            "brand": "Hawk Nelson",
            "sub_categories": [
                "CDs & Vinyl",
                "Christian",
                "Pop & Contemporary"
            ]
        },
        "B00S64V0MO": {
            "title": "Easter At Ephesus",
            "avg_ratings": 5.0,
            "num_ratings": 31,
            "brand": "Benedictines of Mary Queen of Apostles",
            "sub_categories": [
                "CDs & Vinyl",
                "Holiday & Wedding"
            ]
        },
        "B00NU7JFRY": {
            "title": "I Will Trust",
            "avg_ratings": 5.0,
            "num_ratings": 21,
            "brand": "Fred Hammond",
            "sub_categories": [
                "CDs & Vinyl",
                "Pop"
            ]
        }
    },
    "May": {
        "B01F5HXWM0": {
            "title": "Cars",
            "avg_ratings": 5.0,
            "num_ratings": 16,
            "brand": "The Cars",
            "sub_categories": [
                "CDs & Vinyl",
                "Pop"
            ]
        },
        "B01B0NLEK0": {
            "title": "Misty Mountains: Songs Inspired by The Hobbit and Lord of the Rings",
            "avg_ratings": 5.0,
            "num_ratings": 18,
            "brand": "Peter Hollens",
            "sub_categories": [
                "CDs & Vinyl",
                "Pop",
                "Vocal Pop"
            ]
        },
        "B019YQJRKO": {
            "title": "The RCA Albums Collection",
            "avg_ratings": 5.0,
            "num_ratings": 16,
            "brand": "Elvis Presley",
            "sub_categories": [
                "CDs & Vinyl",
                "Pop"
            ]
        },
        "B015C5MFSC": {
            "title": "The Hill",
            "avg_ratings": 5.0,
            "num_ratings": 41,
            "brand": "Travis Greene",
            "sub_categories": [
                "CDs & Vinyl",
                "Pop"
            ]
        },
        "B00VG3NWIW": {
            "title": "New Voices: Brooklyn Art Song Society",
            "avg_ratings": 5.0,
            "num_ratings": 17,
            "brand": "Elisabeth Marshall",
            "sub_categories": [
                "CDs & Vinyl",
                "Classical",
                "Chamber Music"
            ]
        },
        "B00V0CLQ32": {
            "title": "Skeleton Crew",
            "avg_ratings": 5.0,
            "num_ratings": 16,
            "brand": "Madisen Ward & the Mama Bear",
            "sub_categories": [
                "CDs & Vinyl",
                "Folk",
                "Traditional Folk"
            ]
        },
        "B00UKNOKZ8": {
            "title": "Power In The Blood",
            "avg_ratings": 5.0,
            "num_ratings": 15,
            "brand": "Buffy Sainte-Marie",
            "sub_categories": [
                "CDs & Vinyl",
                "Country",
                "Bluegrass"
            ]
        },
        "B00UKC266Y": {
            "title": "The Calming Collection - Calm Mom, Calm Dad, Calm Child: Keeping Your Cool With Your Children, Your Family, and Everyone Else in Your Life",
            "avg_ratings": 5.0,
            "num_ratings": 15,
            "brand": "Roberta Shapiro",
            "sub_categories": [
                "CDs & Vinyl",
                "New Age",
                "Relaxation"
            ]
        },
        "B00SJ9TY9C": {
            "title": "Diamonds",
            "avg_ratings": 5.0,
            "num_ratings": 15,
            "brand": "Hawk Nelson",
            "sub_categories": [
                "CDs & Vinyl",
                "Christian",
                "Pop & Contemporary"
            ]
        },
        "B00P826ZM2": {
            "title": "I Will Follow",
            "avg_ratings": 5.0,
            "num_ratings": 22,
            "brand": "Jeremy Camp",
            "sub_categories": [
                "CDs & Vinyl",
                "Christian",
                "Pop & Contemporary"
            ]
        }
    },
    "Jun": {
        "B01F2TNCYE": {
            "title": "Waitress Original Broadway Cast Recording",
            "avg_ratings": 5.0,
            "num_ratings": 19,
            "brand": "Waitress",
            "sub_categories": [
                "CDs & Vinyl",
                "Broadway & Vocalists",
                "Musicals"
            ]
        },
        "B01CF4KCYC": {
            "title": "Ash & Ice",
            "avg_ratings": 5.0,
            "num_ratings": 15,
            "brand": "The Kills",
            "sub_categories": [
                "CDs & Vinyl",
                "Pop"
            ]
        },
        "B017IXVSJS": {
            "title": "Here As In Heaven",
            "avg_ratings": 5.0,
            "num_ratings": 20,
            "brand": "Elevation Worship",
            "sub_categories": [
                "CDs & Vinyl",
                "Christian",
                "Pop & Contemporary"
            ]
        },
        "B017IXVRX0": {
            "title": "Let It Echo",
            "avg_ratings": 5.0,
            "num_ratings": 15,
            "brand": "Jesus Culture",
            "sub_categories": [
                "CDs & Vinyl",
                "Christian",
                "Pop & Contemporary"
            ]
        },
        "B015ZMV8K8": {
            "title": "What's Inside: Songs From Waitress",
            "avg_ratings": 5.0,
            "num_ratings": 15,
            "brand": "Sara Bareilles",
            "sub_categories": [
                "CDs & Vinyl",
                "Pop"
            ]
        },
        "B014R8BXR4": {
            "title": "I'm Comin' Over",
            "avg_ratings": 5.0,
            "num_ratings": 16,
            "brand": "Chris Young",
            "sub_categories": [
                "CDs & Vinyl",
                "Country"
            ]
        },
        "B00WVMMJS6": {
            "title": "Luminiferous",
            "avg_ratings": 5.0,
            "num_ratings": 16,
            "brand": "High On Fire",
            "sub_categories": [
                "CDs & Vinyl",
                "Metal"
            ]
        },
        "B00WHGJHT0": {
            "title": "Goldmine",
            "avg_ratings": 5.0,
            "num_ratings": 15,
            "brand": "John Anderson",
            "sub_categories": [
                "CDs & Vinyl",
                "Country"
            ]
        },
        "B00M8B8FYM": {
            "title": "WOW Hits 2015",
            "avg_ratings": 5.0,
            "num_ratings": 28,
            "brand": "Various Artists",
            "sub_categories": [
                "CDs & Vinyl",
                "Pop"
            ]
        },
        "B00K98J1E4": {
            "title": "Country Classics: A Tapestry Of Our Musical Heritage",
            "avg_ratings": 5.0,
            "num_ratings": 16,
            "brand": "Joey + Rory",
            "sub_categories": [
                "CDs & Vinyl",
                "Christian",
                "Pop & Contemporary"
            ]
        }
    },
    "Jul": {
        "B01H3KUG9O": {
            "title": "Love Remains",
            "avg_ratings": 5.0,
            "num_ratings": 17,
            "brand": "Hillary Scott and the Scott Family",
            "sub_categories": [
                "CDs & Vinyl",
                "Country"
            ]
        },
        "B01GG2S77S": {
            "title": "Game Of Thrones Music from the HBOr Series Season 6",
            "avg_ratings": 5.0,
            "num_ratings": 16,
            "brand": "Ramin Djawadi",
            "sub_categories": [
                "CDs & Vinyl",
                "Pop"
            ]
        },
        "B01EPN6FNI": {
            "title": "Dress To Impress",
            "avg_ratings": 5.0,
            "num_ratings": 26,
            "brand": "Keith Sweat",
            "sub_categories": [
                "CDs & Vinyl",
                "R&B",
                "Soul"
            ]
        },
        "B017IXVSJS": {
            "title": "Here As In Heaven",
            "avg_ratings": 5.0,
            "num_ratings": 18,
            "brand": "Elevation Worship",
            "sub_categories": [
                "CDs & Vinyl",
                "Christian",
                "Pop & Contemporary"
            ]
        },
        "B0128GGONU": {
            "title": "WOW Hits 2016",
            "avg_ratings": 5.0,
            "num_ratings": 15,
            "brand": "Various Artists",
            "sub_categories": [
                "CDs & Vinyl",
                "Pop"
            ]
        },
        "B00Z0GEU6Y": {
            "title": "Attitude City",
            "avg_ratings": 5.0,
            "num_ratings": 26,
            "brand": "Ninja Sex Party",
            "sub_categories": [
                "CDs & Vinyl",
                "Comedy & Spoken Word",
                "Stand-Up Comedy"
            ]
        },
        "B00WHGJHT0": {
            "title": "Goldmine",
            "avg_ratings": 5.0,
            "num_ratings": 15,
            "brand": "John Anderson",
            "sub_categories": [
                "CDs & Vinyl",
                "Country"
            ]
        },
        "B00V8Q8QTW": {
            "title": "On the Twentieth Century New Broadway Cast Recording",
            "avg_ratings": 5.0,
            "num_ratings": 18,
            "brand": "Kristin Chenoweth",
            "sub_categories": [
                "CDs & Vinyl",
                "Broadway & Vocalists",
                "Musicals"
            ]
        },
        "B00JFJTDXM": {
            "title": "Rewind",
            "avg_ratings": 5.0,
            "num_ratings": 35,
            "brand": "Rascal Flatts",
            "sub_categories": [
                "CDs & Vinyl",
                "Country",
                "Today's Country"
            ]
        },
        "B00JDB4DNC": {
            "title": "The Blues Came Callin' PRD74391",
            "avg_ratings": 5.0,
            "num_ratings": 23,
            "brand": "Walter Trout",
            "sub_categories": [
                "CDs & Vinyl",
                "Blues",
                "Contemporary Blues"
            ]
        }
    },
    "Aug": {
        "B01GKC65HS": {
            "title": "Believe",
            "avg_ratings": 5.0,
            "num_ratings": 16,
            "brand": "Jonathan Antoine",
            "sub_categories": [
                "CDs & Vinyl",
                "Classical"
            ]
        },
        "B01FND51HK": {
            "title": "TROLLS Soundtrack",
            "avg_ratings": 5.0,
            "num_ratings": 30,
            "brand": "Various Artists",
            "sub_categories": [
                "CDs & Vinyl",
                "Soundtracks",
                "Movie Scores"
            ]
        },
        "B01E6B1EYY": {
            "title": "Joan Baez 75th Birthday Celebration",
            "avg_ratings": 5.0,
            "num_ratings": 17,
            "brand": "Joan Baez",
            "sub_categories": [
                "CDs & Vinyl",
                "Folk",
                "Traditional Folk"
            ]
        },
        "B01BP47HGO": {
            "title": "The River",
            "avg_ratings": 5.0,
            "num_ratings": 19,
            "brand": "Jordan Feliz",
            "sub_categories": [
                "CDs & Vinyl",
                "Christian",
                "Pop & Contemporary"
            ]
        },
        "B0183W1OZQ": {
            "title": "Life Screams",
            "avg_ratings": 5.0,
            "num_ratings": 19,
            "brand": "Lacey Sturm",
            "sub_categories": [
                "CDs & Vinyl",
                "Pop"
            ]
        },
        "B015C5MFSC": {
            "title": "The Hill",
            "avg_ratings": 5.0,
            "num_ratings": 23,
            "brand": "Travis Greene",
            "sub_categories": [
                "CDs & Vinyl",
                "Pop"
            ]
        },
        "B012WBL41S": {
            "title": "Grande amore",
            "avg_ratings": 5.0,
            "num_ratings": 16,
            "brand": "Il Volo",
            "sub_categories": [
                "CDs & Vinyl",
                "Latin Music",
                "Latin Pop"
            ]
        },
        "B0128GGONU": {
            "title": "WOW Hits 2016",
            "avg_ratings": 5.0,
            "num_ratings": 20,
            "brand": "Various Artists",
            "sub_categories": [
                "CDs & Vinyl",
                "Pop"
            ]
        },
        "B00KYVHFT4": {
            "title": "Anchor",
            "avg_ratings": 5.0,
            "num_ratings": 18,
            "brand": "Colton Dixon",
            "sub_categories": [
                "CDs & Vinyl",
                "Christian",
                "Pop & Contemporary"
            ]
        },
        "B00KB48SSQ": {
            "title": "Performs Trouble No More Live At Town Hall",
            "avg_ratings": 5.0,
            "num_ratings": 16,
            "brand": "John Mellencamp",
            "sub_categories": [
                "CDs & Vinyl",
                "Pop"
            ]
        }
    },
    "Sep": {
        "B01H4TUWH0": {
            "title": "I'm Not The Devil",
            "avg_ratings": 5.0,
            "num_ratings": 22,
            "brand": "Cody Jinks",
            "sub_categories": [
                "CDs & Vinyl",
                "Country"
            ]
        },
        "B014PD0R0A": {
            "title": "Pentatonix Deluxe Version",
            "avg_ratings": 5.0,
            "num_ratings": 17,
            "brand": "Pentatonix",
            "sub_categories": [
                "CDs & Vinyl",
                "Pop",
                "Vocal Pop"
            ]
        },
        "B012YMLCUS": {
            "title": "Wild EP",
            "avg_ratings": 5.0,
            "num_ratings": 25,
            "brand": "Troye Sivan",
            "sub_categories": [
                "CDs & Vinyl",
                "Pop"
            ]
        },
        "B011Y2MI1G": {
            "title": "Remembering Mr. Sinatra",
            "avg_ratings": 5.0,
            "num_ratings": 16,
            "brand": "Julie Budd",
            "sub_categories": [
                "CDs & Vinyl",
                "Pop",
                "Easy Listening"
            ]
        },
        "B00Y2TEILC": {
            "title": "Men Amongst Mountains",
            "avg_ratings": 5.0,
            "num_ratings": 17,
            "brand": "The Revivalists",
            "sub_categories": [
                "CDs & Vinyl",
                "Pop"
            ]
        },
        "B00XWSL8DA": {
            "title": "Play This Intimately As If Among Friends  Translucent",
            "avg_ratings": 5.0,
            "num_ratings": 37,
            "brand": "Pugwash",
            "sub_categories": [
                "CDs & Vinyl",
                "Pop"
            ]
        },
        "B00VRMEOKW": {
            "title": "Start Here",
            "avg_ratings": 5.0,
            "num_ratings": 16,
            "brand": "Maddie & Tae",
            "sub_categories": [
                "CDs & Vinyl",
                "Country"
            ]
        },
        "B00RO5LVIY": {
            "title": "Life Music: Stage Two",
            "avg_ratings": 5.0,
            "num_ratings": 18,
            "brand": "Jonathan McReynolds",
            "sub_categories": [
                "CDs & Vinyl",
                "Pop"
            ]
        },
        "B00P82BE6E": {
            "title": "We Will Not Be Shaken",
            "avg_ratings": 5.0,
            "num_ratings": 17,
            "brand": "Bethel Music",
            "sub_categories": [
                "CDs & Vinyl",
                "Christian",
                "Pop & Contemporary"
            ]
        },
        "B00O0MBH42": {
            "title": "Greatest Hits: Decade #1",
            "avg_ratings": 5.0,
            "num_ratings": 24,
            "brand": "Carrie Underwood",
            "sub_categories": [
                "CDs & Vinyl",
                "Country",
                "Today's Country"
            ]
        }
    },
    "Oct": {
        "B01C6KM1XK": {
            "title": "Take Me To The Alley",
            "avg_ratings": 5.0,
            "num_ratings": 19,
            "brand": "Gregory Porter",
            "sub_categories": [
                "CDs & Vinyl",
                "Jazz"
            ]
        },
        "B012SVTV2Q": {
            "title": "Until The Whole World Hears",
            "avg_ratings": 5.0,
            "num_ratings": 21,
            "brand": "Casting Crowns",
            "sub_categories": [
                "CDs & Vinyl",
                "Christian",
                "Pop & Contemporary"
            ]
        },
        "B012BE333I": {
            "title": "Lalah Hathaway Live",
            "avg_ratings": 5.0,
            "num_ratings": 19,
            "brand": "Lalah Hathaway",
            "sub_categories": [
                "CDs & Vinyl",
                "R&B",
                "Soul"
            ]
        },
        "B010QCGBIQ": {
            "title": "Live In LA",
            "avg_ratings": 5.0,
            "num_ratings": 16,
            "brand": "Gino Vannelli",
            "sub_categories": [
                "CDs & Vinyl",
                "Pop"
            ]
        },
        "B00NCGXYJS": {
            "title": "It's the Girls!",
            "avg_ratings": 5.0,
            "num_ratings": 18,
            "brand": "Bette Midler",
            "sub_categories": [
                "CDs & Vinyl",
                "Pop",
                "Vocal Pop"
            ]
        },
        "B00M0CVY92": {
            "title": "A Skeletal Domain",
            "avg_ratings": 5.0,
            "num_ratings": 15,
            "brand": "Cannibal Corpse",
            "sub_categories": [
                "CDs & Vinyl",
                "Pop"
            ]
        },
        "B00K98J1E4": {
            "title": "Country Classics: A Tapestry Of Our Musical Heritage",
            "avg_ratings": 5.0,
            "num_ratings": 15,
            "brand": "Joey + Rory",
            "sub_categories": [
                "CDs & Vinyl",
                "Christian",
                "Pop & Contemporary"
            ]
        },
        "B00IS6ECGQ": {
            "title": "Wild Ones",
            "avg_ratings": 5.0,
            "num_ratings": 20,
            "brand": "Kip Moore",
            "sub_categories": [
                "CDs & Vinyl",
                "Country"
            ]
        },
        "B00HQRYJE8": {
            "title": "Riser",
            "avg_ratings": 5.0,
            "num_ratings": 18,
            "brand": "Dierks Bentley",
            "sub_categories": [
                "CDs & Vinyl",
                "Country",
                "Today's Country"
            ]
        },
        "B00DJYJX2K": {
            "title": "Essential Tremors",
            "avg_ratings": 5.0,
            "num_ratings": 16,
            "brand": "J Roddy Walston & The Business",
            "sub_categories": [
                "CDs & Vinyl",
                "Pop"
            ]
        }
    },
    "Nov": {
        "B01GKC65HS": {
            "title": "Believe",
            "avg_ratings": 5.0,
            "num_ratings": 15,
            "brand": "Jonathan Antoine",
            "sub_categories": [
                "CDs & Vinyl",
                "Classical"
            ]
        },
        "B017B7KW4I": {
            "title": "Winter Symphony",
            "avg_ratings": 5.0,
            "num_ratings": 35,
            "brand": "Jennifer Thomas",
            "sub_categories": [
                "CDs & Vinyl",
                "Holiday & Wedding"
            ]
        },
        "B0130HVMWE": {
            "title": "On Purpose",
            "avg_ratings": 5.0,
            "num_ratings": 17,
            "brand": "Clint Black",
            "sub_categories": [
                "CDs & Vinyl",
                "Country"
            ]
        },
        "B011LNVGMA": {
            "title": "Get Weird",
            "avg_ratings": 5.0,
            "num_ratings": 19,
            "brand": "Little Mix",
            "sub_categories": [
                "CDs & Vinyl",
                "Pop"
            ]
        },
        "B00XRFT5PG": {
            "title": "The Woman Astronaut",
            "avg_ratings": 5.0,
            "num_ratings": 15,
            "brand": "Penka Kouneva",
            "sub_categories": [
                "CDs & Vinyl",
                "Pop"
            ]
        },
        "B00VTBBEL8": {
            "title": "Angels And Alcohol",
            "avg_ratings": 5.0,
            "num_ratings": 21,
            "brand": "Alan Jackson",
            "sub_categories": [
                "CDs & Vinyl",
                "Country"
            ]
        },
        "B00NXKZFI6": {
            "title": "Christmas With Friends",
            "avg_ratings": 5.0,
            "num_ratings": 17,
            "brand": "India Arie",
            "sub_categories": [
                "CDs & Vinyl",
                "R&B",
                "Soul"
            ]
        },
        "B00NMNX9WS": {
            "title": "A Very Maysa Christmas",
            "avg_ratings": 5.0,
            "num_ratings": 16,
            "brand": "Maysa",
            "sub_categories": [
                "CDs & Vinyl",
                "Jazz"
            ]
        },
        "B00H9MGWUO": {
            "title": "Hidden in My Heart, Volume III, A Lullaby Journey Through The Life Of Jesus",
            "avg_ratings": 5.0,
            "num_ratings": 21,
            "brand": null,
            "sub_categories": [
                "CDs & Vinyl",
                "Christian",
                "Praise & Worship"
            ]
        },
        "B00EULQJXM": {
            "title": "Sending You a Little Christmas",
            "avg_ratings": 5.0,
            "num_ratings": 30,
            "brand": "Johnny Mathis",
            "sub_categories": [
                "CDs & Vinyl",
                "Holiday & Wedding",
                "Christmas"
            ]
        }
    },
    "Dec": {
        "B01AM6JWUU": {
            "title": "Blues Of Desperation: Deluxe",
            "avg_ratings": 5.0,
            "num_ratings": 25,
            "brand": "Joe Bonamassa",
            "sub_categories": [
                "CDs & Vinyl",
                "Blues"
            ]
        },
        "B0161H1K8G": {
            "title": "Nightbird",
            "avg_ratings": 5.0,
            "num_ratings": 19,
            "brand": "Eva Cassidy",
            "sub_categories": [
                "CDs & Vinyl",
                "Pop"
            ]
        },
        "B014L2YF26": {
            "title": "KIDZ BOP 30",
            "avg_ratings": 5.0,
            "num_ratings": 33,
            "brand": "KIDZ BOP Kids",
            "sub_categories": [
                "CDs & Vinyl",
                "Children's Music"
            ]
        },
        "B0147Y0JSM": {
            "title": "Nine Track Mind",
            "avg_ratings": 5.0,
            "num_ratings": 16,
            "brand": "Charlie Puth",
            "sub_categories": [
                "CDs & Vinyl",
                "Pop"
            ]
        },
        "B00VTBBEL8": {
            "title": "Angels And Alcohol",
            "avg_ratings": 5.0,
            "num_ratings": 15,
            "brand": "Alan Jackson",
            "sub_categories": [
                "CDs & Vinyl",
                "Country"
            ]
        },
        "B00P82BE6E": {
            "title": "We Will Not Be Shaken",
            "avg_ratings": 5.0,
            "num_ratings": 17,
            "brand": "Bethel Music",
            "sub_categories": [
                "CDs & Vinyl",
                "Christian",
                "Pop & Contemporary"
            ]
        },
        "B00OMBJYR8": {
            "title": "Everlasting",
            "avg_ratings": 5.0,
            "num_ratings": 17,
            "brand": "Collin Raye",
            "sub_categories": [
                "CDs & Vinyl",
                "Country"
            ]
        },
        "B00NF4PPCG": {
            "title": "All of My Memories",
            "avg_ratings": 5.0,
            "num_ratings": 28,
            "brand": "John Denver",
            "sub_categories": [
                "CDs & Vinyl",
                "Country"
            ]
        },
        "B00K5P33O0": {
            "title": "Nothing More",
            "avg_ratings": 5.0,
            "num_ratings": 20,
            "brand": "Nothing More",
            "sub_categories": [
                "CDs & Vinyl",
                "Pop"
            ]
        },
        "B00H9MGWUO": {
            "title": "Hidden in My Heart, Volume III, A Lullaby Journey Through The Life Of Jesus",
            "avg_ratings": 5.0,
            "num_ratings": 25,
            "brand": null,
            "sub_categories": [
                "CDs & Vinyl",
                "Christian",
                "Praise & Worship"
            ]
        }
    }
}